pesel/__init__.py
pesel/__main__.py
pesel/main.py
pesel/pesel.py
pesel-0.3.1.dist-info/LICENSE
pesel-0.3.1.dist-info/METADATA
pesel-0.3.1.dist-info/WHEEL
pesel-0.3.1.dist-info/entry_points.txt
pesel-0.3.1.dist-info/top_level.txt
pesel-0.3.1.dist-info/RECORD
