Metadata-Version: 2.1
Name: pesel
Version: 0.3.1
Summary: Polish PESEL
Home-page: https://github.com/jsporna/pypesel
Author: Jakub Spórna <jakub.sporna@gmail.com>
Author-email: jakub@sporna.dev
License: UNKNOWN
Keywords: pesel
Platform: UNKNOWN
Classifier: License :: OSI Approved :: Apache Software License
Classifier: Programming Language :: Python :: 3
Classifier: Programming Language :: Python :: 3.8
Classifier: Programming Language :: Python :: Implementation :: CPython
